nonebot_plugin_guess/__init__.py
nonebot_plugin_guess/config.py
nonebot_plugin_guess/guess.py
nonebot_plugin_guess-0.1.9.dist-info/WHEEL
nonebot_plugin_guess-0.1.9.dist-info/METADATA
nonebot_plugin_guess-0.1.9.dist-info/RECORD
