Metadata-Version: 2.1
Name: nonebot-plugin-guess
Version: 0.1.9
Summary: nobebot2插件《猜猜看》
Home-page: https://github.com/ffreemt/nonebot-plugin-guess-game
License: MIT
Author: freemt
Requires-Python: >=3.7.3,<4.0.0
Classifier: License :: OSI Approved :: MIT License
Classifier: Programming Language :: Python :: 3
Classifier: Programming Language :: Python :: 3.8
Classifier: Programming Language :: Python :: 3.9
Classifier: Programming Language :: Python :: 3.10
Requires-Dist: joblib (>=1.0.1,<2.0.0)
Requires-Dist: logzero (>=1.6.3,<2.0.0)
Requires-Dist: nonebot-adapter-onebot (>=2.0.0-beta.1,<3.0.0)
Requires-Dist: nonebot2 (>=2.0.0-beta.2,<3.0.0)
Requires-Dist: pydantic[dotenv] (>=1.8.1,<2.0.0)
Requires-Dist: pyquery (>=1.4.3,<2.0.0)
Requires-Dist: pytz (>=2021.1,<2022.0)
Project-URL: Repository, https://github.com/ffreemt/nonebot-plugin-guess-game
